mollie_api_extract/__init__.py
mollie_api_extract/functionlist.py
mollie_api_extract/sumxy.py
mollie_api_extract-1.0.2.dist-info/LICENSE.txt
mollie_api_extract-1.0.2.dist-info/METADATA
mollie_api_extract-1.0.2.dist-info/WHEEL
mollie_api_extract-1.0.2.dist-info/top_level.txt
mollie_api_extract-1.0.2.dist-info/RECORD
