Metadata-Version: 2.1
Name: mollie-api-extract
Version: 1.0.2
Summary: Fetch data from your Mollie account
Home-page: https://github.com/amodk/development_packages/tree/master/mollie_api_extract
Author: Amod Kumar
Author-email: amodk@outlook.com
License: UNKNOWN
Platform: UNKNOWN
Classifier: Programming Language :: Python :: 3
Classifier: License :: OSI Approved :: MIT License
Classifier: Operating System :: OS Independent
Requires-Python: >=3.6
Requires-Dist: pandas
Requires-Dist: requests
